feffery_infographic/Infographic.py
feffery_infographic/__init__.py
feffery_infographic/_imports_.py
feffery_infographic/feffery_infographic.min.js
feffery_infographic/feffery_infographic.min.js.LICENSE.txt
feffery_infographic/feffery_infographic.min.js.map
feffery_infographic/metadata.json
feffery_infographic/package-info.json
feffery_infographic/prompts.py
feffery_infographic-0.1.5.dist-info/licenses/LICENSE
feffery_infographic-0.1.5.dist-info/METADATA
feffery_infographic-0.1.5.dist-info/WHEEL
feffery_infographic-0.1.5.dist-info/top_level.txt
feffery_infographic-0.1.5.dist-info/RECORD
