Metadata-Version: 2.4
Name: feffery_infographic
Version: 0.1.5
Summary: Plotly Dash components based on AntV Infographic
Home-page: https://github.com/HogaStack/feffery-infographic
Author: CNFeffery <fefferypzy@gmail.com>
License: MIT
Classifier: Framework :: Dash
License-File: LICENSE
Requires-Dist: dash>=3.3.0
Dynamic: author
Dynamic: classifier
Dynamic: description
Dynamic: description-content-type
Dynamic: home-page
Dynamic: license
Dynamic: license-file
Dynamic: requires-dist
Dynamic: summary
